deepcase/__init__.py
deepcase/__main__.py
deepcase/deepcase2.py
deepcase/module.py
deepcase/utils.py
deepcase/context_builder/__init__.py
deepcase/context_builder/context_builder.py
deepcase/context_builder/decoders.py
deepcase/context_builder/embedding.py
deepcase/context_builder/encoders.py
deepcase/context_builder/loss.py
deepcase/context_builder/optimizer.py
deepcase/context_builder/utils.py
deepcase/interpreter/__init__.py
deepcase/interpreter/cluster.py
deepcase/interpreter/interpreter.py
deepcase/interpreter/utils.py
deepcase/preprocessing/__init__.py
deepcase/preprocessing/preprocessor.py
deepcase-1.0.1.dist-info/LICENSE
deepcase-1.0.1.dist-info/METADATA
deepcase-1.0.1.dist-info/WHEEL
deepcase-1.0.1.dist-info/top_level.txt
deepcase-1.0.1.dist-info/RECORD
