Metadata-Version: 2.1
Name: deepcase
Version: 1.0.1
Summary: DeepCASE: Semi-Supervised Contextual Analysis of Security Events
Home-page: https://github.com/Thijsvanede/DeepCASE
Author: Thijs van Ede
Author-email: t.s.vanede@utwente.nl
License: UNKNOWN
Platform: UNKNOWN
Classifier: Programming Language :: Python :: 3
Classifier: License :: OSI Approved :: MIT License
Classifier: Operating System :: OS Independent
